<annotation>
	<folder>cccd</folder>
	<filename>16__blur2.0.jpg</filename>
	<path>D:\testAI\cccd\16__blur2.0.jpg</path>
	<source>
		<database>Unknown</database>
	</source>
	<size>
		<width>2048</width>
		<height>1534</height>
		<depth>3</depth>
	</size>
	<segmented>0</segmented>
	<object>
		<name>top_left</name>
		<pose>Unspecified</pose>
		<truncated>0</truncated>
		<difficult>0</difficult>
		<bndbox>
			<xmin>129</xmin>
			<ymin>305</ymin>
			<xmax>198</xmax>
			<ymax>380</ymax>
		</bndbox>
	</object>
	<object>
		<name>top_right</name>
		<pose>Unspecified</pose>
		<truncated>0</truncated>
		<difficult>0</difficult>
		<bndbox>
			<xmin>1854</xmin>
			<ymin>309</ymin>
			<xmax>1936</xmax>
			<ymax>385</ymax>
		</bndbox>
	</object>
	<object>
		<name>bottom_right</name>
		<pose>Unspecified</pose>
		<truncated>0</truncated>
		<difficult>0</difficult>
		<bndbox>
			<xmin>1892</xmin>
			<ymin>1400</ymin>
			<xmax>1963</xmax>
			<ymax>1474</ymax>
		</bndbox>
	</object>
	<object>
		<name>bottom_left</name>
		<pose>Unspecified</pose>
		<truncated>0</truncated>
		<difficult>0</difficult>
		<bndbox>
			<xmin>89</xmin>
			<ymin>1409</ymin>
			<xmax>207</xmax>
			<ymax>1476</ymax>
		</bndbox>
	</object>
</annotation>
